[
    {
        "title": "Total Clips",
        "count": 7030
    },
    {
        "title": "Total Topics",
        "count": 455
    },
    {
        "title": "Number of days worth of source streams & videos indexed",
        "count": 215
    },
    {
        "title": "Clips probably having standard description",
        "progress": "0.580512",
        "percentage": "58.05"
    },
    {
        "title": "Clips with any transcription",
        "progress": "0.850640",
        "percentage": "85.06"
    },
    {
        "title": "Clips with structured transcription",
        "progress": "0.002702",
        "percentage": "0.27"
    },
    {
        "title": "Topics with structured data",
        "progress": "0.140659",
        "percentage": "14.06"
    }
]